{
  "التعليم_الديني": {
    "الوصف": "تعليم إسلامي صحيح قائم على القرآن والسنة فقط",
    "الفروع": {
      "القرآن_الكريم": ["تلاوة", "تجويد", "تفسير مبسط", "حفظ"],
      "السنة_النبوية": ["أحاديث صحيحة", "شرح الحديث", "السيرة النبوية"],
      "الفقه": ["العبادات", "المعاملات", "فقه الأسرة"],
      "العقيدة": ["التوحيد", "الإيمان", "تصحيح المفاهيم"],
      "الأخلاق_والآداب": ["التربية الإسلامية", "تعليم الأطفال", "الرد على الشبهات", "فقه الواقع", "الاقتصاد الإسلامي"]
    }
  },
  "المهارات_الرقمية": {
    "الوصف": "مهارات سوق العمل الحديث",
    "الفروع": {
      "البرمجة": ["HTML / CSS", "JavaScript", "Python", "PHP", "Java", "تطوير الويب", "تطوير التطبيقات"],
      "الذكاء_الاصطناعي": ["تحليل البيانات", "أمن سيبراني"],
      "التصميم": ["UI / UX", "تصميم جرافيكي", "مونتاج وصناعة فيديو"],
      "العمل_الحر": ["Fiverr", "Upwork", "التسويق الرقمي", "إدارة المشاريع الرقمية"]
    }
  },
  "الكمبيوتر": {
    "الوصف": "هارد وير / سوفت وير",
    "الفروع": {
      "أساسيات_الكمبيوتر": ["أنظمة التشغيل", "Windows", "Linux"],
      "صيانة_الكمبيوتر": ["تجميع الكمبيوتر", "الشبكات", "السيرفرات", "استكشاف الأخطاء", "تعريفات الأجهزة", "حماية الجهاز من الفيروسات", "النسخ الاحتياطي"]
    }
  },
  "صيانة_الموبايلات": {
    "الوصف": "صيانة أجهزة الموبايل",
    "الفروع": {
      "أساسيات_الصيانة": ["فك وتركيب", "السوفت وير", "تفليش", "أنظمة Android", "أنظمة iOS"],
      "الأعطال": ["أعطال الشاشة", "أعطال البطارية", "أعطال الشحن", "أعطال الشبكة"],
      "صيانة_أجهزة_تابلت": ["أدوات الصيانة", "فتح مشروع صيانة"]
    }
  },
  "صيانة_الأجهزة_المنزلية": {
    "الوصف": "صيانة الأجهزة المنزلية",
    "الفروع": ["غسالات", "ثلاجات", "سخانات", "ميكروويف", "مكيفات", "أفران", "أجهزة كهربائية أخرى"]
  },
  "المهن_الحرفية": {
    "الوصف": "مهارات عملية ومهنية",
    "الفروع": ["كهرباء", "سباكة", "نجارة", "حدادة", "ألوميتال", "تبريد وتكييف", "دهانات", "محارة", "بلاط وسيراميك", "صيانة أجهزة منزلية"]
  },
  "الصناعة": {
    "الوصف": "أساسيات الصناعة",
    "الفروع": ["السلامة المهنية", "خطوط الإنتاج", "التصنيع الغذائي", "الصناعات البلاستيكية", "الصناعات المعدنية", "الصناعات الكيميائية", "الصناعات الدوائية", "إدارة المصانع", "الجودة ISO", "الصيانة الصناعية"]
  },
  "التجارة": {
    "الوصف": "التجارة التقليدية والإلكترونية",
    "الفروع": ["التجارة التقليدية", "التجارة الإلكترونية", "البيع والشراء", "الاستيراد والتصدير", "إدارة المخزون", "التسعير", "التفاوض", "التسويق التجاري", "التجارة الحلال", "إدارة المتاجر"]
  },
  "الاقتصاد": {
    "الوصف": "مبادئ الاقتصاد",
    "الفروع": ["الاقتصاد الإسلامي", "الاقتصاد الجزئي", "الاقتصاد الكلي", "الأسواق المالية", "إدارة الأموال", "الادخار", "الاستثمار الحلال", "ريادة الأعمال", "المشاريع الصغيرة"]
  },
  "العلوم": {
    "الوصف": "علوم عامة وتجارب مبسطة",
    "الفروع": ["الفيزياء", "الكيمياء", "الأحياء", "الجيولوجيا", "الفلك", "التجارب العلمية", "تبسيط العلوم", "العلوم للأطفال"]
  },
  "اللغات": {
    "الوصف": "تعلم لغات مختلفة",
    "الفروع": ["الإنجليزية", "الفرنسية", "الألمانية", "التركية", "الإسبانية", "الصينية", "العربية لغير الناطقين بها", "الترجمة", "المحادثة", "المصطلحات المهنية"]
  },
  "الصناعات_اليدوية": {
    "الوصف": "إبداع وأشغال يدوية",
    "الفروع": ["الحياكة", "الكروشيه", "التطريز", "الأشغال الخشبية", "الفخار", "الإكسسوارات", "إعادة التدوير", "المشغولات الفنية", "تسويق المنتجات اليدوية"]
  },
  "التكنولوجيا": {
    "الوصف": "التقنيات الحديثة",
    "الفروع": ["تكنولوجيا المعلومات", "إنترنت الأشياء IoT", "البلوك تشين", "Web3", "العملات الرقمية التعليمية", "الأنظمة الذكية", "الحوسبة السحابية", "الروبوتات", "الواقع الافتراضي", "التكنولوجيا التعليمية"]
  },
  "الجواز_في_الحلال": {
    "الوصف": "تسهيل الزواج الشرعي",
    "الفروع": ["طلب زواج شرعي", "عرض بيانات الزواج", "التوفيق بين الطرفين", "الإرشاد الأسري", "ثقافة الزواج", "تربية الأبناء", "حل الخلافات", "ضوابط شرعية صارمة", "بدون دردشات محرمة", "إشراف إداري كامل"]
  }
}
